freyja/__init__.py
freyja/cli/__init__.py
freyja/cli/system/__init__.py
freyja/cli/system/completion.py
freyja/cli/system/completion_installer.py
freyja/cli/system/system_class_builder.py
freyja/cli/system/tune_theme.py
freyja/cli/target_mode_enum.py
freyja/command/__init__.py
freyja/command/class_handler.py
freyja/command/command_discovery.py
freyja/command/command_executor.py
freyja/command/command_parser.py
freyja/command/execution_coordinator.py
freyja/command/validation_service.py
freyja/completion/__init__.py
freyja/completion/base.py
freyja/completion/bash.py
freyja/completion/fish.py
freyja/completion/installer.py
freyja/completion/powershell.py
freyja/completion/zsh.py
freyja/examples/cls_example
freyja/examples/multi_class_example
freyja/examples/system_example
freyja/freyja_cli.py
freyja/help/__init__.py
freyja/help/format_patterns.py
freyja/help/help_formatter.py
freyja/help/help_formatting_engine.py
freyja/parser/__init__.py
freyja/parser/argument_parser.py
freyja/parser/argument_preprocessor.py
freyja/parser/docstring_parser.py
freyja/parser/option_discovery.py
freyja/parser/positional_handler.py
freyja/shared/__init__.py
freyja/shared/command_info.py
freyja/shared/command_tree.py
freyja/theme/__init__.py
freyja/theme/adjust_strategy.py
freyja/theme/back.py
freyja/theme/color_formatter.py
freyja/theme/command_style_section.py
freyja/theme/defaults.py
freyja/theme/fore.py
freyja/theme/fore_universal.py
freyja/theme/rgb.py
freyja/theme/style_enum.py
freyja/theme/theme.py
freyja/theme/theme_style.py
freyja/utils/__init__.py
freyja/utils/ansi_string.py
freyja/utils/app_logger.py
freyja/utils/console_formatter.py
freyja/utils/data_struct_util.py
freyja/utils/dependency_analyzer.py
freyja/utils/json_formatter.py
freyja/utils/math_util.py
freyja/utils/output_capture.py
freyja/utils/spinner.py
freyja/utils/text_util.py
freyja/utils/version.py
freyja-1.2.4.dist-info/METADATA
freyja-1.2.4.dist-info/WHEEL
freyja-1.2.4.dist-info/licenses/LICENSE
freyja-1.2.4.dist-info/RECORD
