Metadata-Version: 2.4
Name: freyja
Version: 1.2.4
Summary: Python Library that builds a complete CLI given one or more functions using introspection
License-Expression: MIT
License-File: LICENSE
Keywords: cli,auto,introspection,argparse,command-line
Author: steven.miers@gmail.com
Requires-Python: >=3.13.7,<4.0.0
Classifier: Development Status :: 4 - Beta
Classifier: Intended Audience :: Developers
Classifier: License :: OSI Approved :: MIT License
Classifier: Operating System :: OS Independent
Classifier: Programming Language :: Python :: 3
Classifier: Programming Language :: Python :: 3.14
Classifier: Programming Language :: Python :: 3.13
Classifier: Topic :: Software Development :: Libraries :: Python Modules
Classifier: Topic :: System :: Systems Administration
Classifier: Topic :: Utilities
Project-URL: Documentation, https://github.com/terracoil/freyja/tree/main/docs
Project-URL: Homepage, https://github.com/terracoil/freyja
Project-URL: Repository, https://github.com/terracoil/freyja
